_randall.cpython-39-darwin.so
randall/__init__.py
randall-0.0.0.dist-info/LICENSE
randall-0.0.0.dist-info/METADATA
randall-0.0.0.dist-info/WHEEL
randall-0.0.0.dist-info/top_level.txt
randall-0.0.0.dist-info/RECORD
